task1/counter.sv
module counter #(
    parameter WIDTH = 8
)(
    // interface signals
    input   logic               clk,    // clock
    input   logic               rst,    // reset
    input   logic               en,     // counter enable
    output  logic [WIDTH-1:0]   count   // counter output
);

always_ff @(posedge clk, posedge rst)
    if (rst)    count <= {WIDTH{1'b0}};
    else        count <= count + {{WIDTH-1{1'b0}}, en};

endmodule

task1/counter.vcd
$version Generated by VerilatedVcd $end
$date Wed Nov  2 15:39:12 2022 $end
$timescale 1ps $end

 $scope module TOP $end
  $var wire  1 # clk $end
  $var wire  8 & count [7:0] $end
  $var wire  1 % en $end
  $var wire  1 $ rst $end
  $scope module counter $end
   $var wire 32 ' WIDTH [31:0] $end
   $var wire  1 # clk $end
   $var wire  8 & count [7:0] $end
   $var wire  1 % en $end
   $var wire  1 $ rst $end
  $upscope $end
 $upscope $end
$enddefinitions $end


#0
1#
1$
0%
b00000000 &
b00000000000000000000000000001000 '
#2
0#
#4
#6
0$
#8
#10
#12
1%
#14
b00000001 &
#16
b00000010 &
#18
b00000011 &
#20
b00000100 &
#22
b00000101 &
#24
b00000110 &
#26
b00000111 &
#28
b00001000 &
#30
0%
b00001001 &
#32
#34
#36
1%
#38
b00001010 &
#40
b00001011 &
#42
b00001100 &
#44
b00001101 &
#46
b00001110 &
#48
b00001111 &
#50
b00010000 &
#52
b00010001 &
#54
b00010010 &
#56
b00010011 &
#58
b00010100 &
#60
b00010101 &
#62
b00010110 &
#64
b00010111 &
#66
b00011000 &
#68
b00011001 &
#70
b00011010 &
#72
b00011011 &
#74
b00011100 &
#76
b00011101 &
#78
b00011110 &
#80
b00011111 &
#82
b00100000 &
#84
b00100001 &
#86
b00100010 &
#88
b00100011 &
#90
b00100100 &
#92
b00100101 &
#94
b00100110 &
#96
b00100111 &
#98
b00101000 &
#100
b00101001 &
#102
b00101010 &
#104
b00101011 &
#106
b00101100 &
#108
b00101101 &
#110
b00101110 &
#112
b00101111 &
#114
b00110000 &
#116
b00110001 &
#118
b00110010 &
#120
b00110011 &
#122
b00110100 &
#124
b00110101 &
#126
b00110110 &
#128
b00110111 &
#130
b00111000 &
#132
b00111001 &
#134
b00111010 &
#136
b00111011 &
#138
b00111100 &
#140
b00111101 &
#142
b00111110 &
#144
b00111111 &
#146
b01000000 &
#148
b01000001 &
#150
b01000010 &
#152
b01000011 &
#154
b01000100 &
#156
b01000101 &
#158
b01000110 &
#160
b01000111 &
#162
b01001000 &
#164
b01001001 &
#166
b01001010 &
#168
b01001011 &
#170
b01001100 &
#172
b01001101 &
#174
b01001110 &
#176
b01001111 &
#178
b01010000 &
#180
b01010001 &
#182
b01010010 &
#184
b01010011 &
#186
b01010100 &
#188
b01010101 &
#190
b01010110 &
#192
b01010111 &
#194
b01011000 &
#196
b01011001 &
#198
b01011010 &
#200
b01011011 &
#202
b01011100 &
#204
b01011101 &
#206
b01011110 &
#208
b01011111 &
#210
b01100000 &
#212
b01100001 &
#214
b01100010 &
#216
b01100011 &
#218
b01100100 &
#220
b01100101 &
#222
b01100110 &
#224
b01100111 &
#226
b01101000 &
#228
b01101001 &
#230
b01101010 &
#232
b01101011 &
#234
b01101100 &
#236
b01101101 &
#238
b01101110 &
#240
b01101111 &
#242
b01110000 &
#244
b01110001 &
#246
b01110010 &
#248
b01110011 &
#250
b01110100 &
#252
b01110101 &
#254
b01110110 &
#256
b01110111 &
#258
b01111000 &
#260
b01111001 &
#262
b01111010 &
#264
b01111011 &
#266
b01111100 &
#268
b01111101 &
#270
b01111110 &
#272
b01111111 &
#274
b10000000 &
#276
b10000001 &
#278
b10000010 &
#280
b10000011 &
#282
b10000100 &
#284
b10000101 &
#286
b10000110 &
#288
b10000111 &
#290
b10001000 &
#292
b10001001 &
#294
b10001010 &
#296
b10001011 &
#298
b10001100 &
#300
b10001101 &
#302
b10001110 &
#304
b10001111 &
#306
b10010000 &
#308
b10010001 &
#310
b10010010 &
#312
b10010011 &
#314
b10010100 &
#316
b10010101 &
#318
b10010110 &
#320
b10010111 &
#322
b10011000 &
#324
b10011001 &
#326
b10011010 &
#328
b10011011 &
#330
b10011100 &
#332
b10011101 &
#334
b10011110 &
#336
b10011111 &
#338
b10100000 &
#340
b10100001 &
#342
b10100010 &
#344
b10100011 &
#346
b10100100 &
#348
b10100101 &
#350
b10100110 &
#352
b10100111 &
#354
b10101000 &
#356
b10101001 &
#358
b10101010 &
#360
b10101011 &
#362
b10101100 &
#364
b10101101 &
#366
b10101110 &
#368
b10101111 &
#370
b10110000 &
#372
b10110001 &
#374
b10110010 &
#376
b10110011 &
#378
b10110100 &
#380
b10110101 &
#382
b10110110 &
#384
b10110111 &
#386
b10111000 &
#388
b10111001 &
#390
b10111010 &
#392
b10111011 &
#394
b10111100 &
#396
b10111101 &
#398
b10111110 &
#400
b10111111 &
#402
b11000000 &
#404
b11000001 &
#406
b11000010 &
#408
b11000011 &
#410
b11000100 &
#412
b11000101 &
#414
b11000110 &
#416
b11000111 &
#418
b11001000 &
#420
b11001001 &
#422
b11001010 &
#424
b11001011 &
#426
b11001100 &
#428
b11001101 &
#430
b11001110 &
#432
b11001111 &
#434
b11010000 &
#436
b11010001 &
#438
b11010010 &
#440
b11010011 &
#442
b11010100 &
#444
b11010101 &
#446
b11010110 &
#448
b11010111 &
#450
b11011000 &
#452
b11011001 &
#454
b11011010 &
#456
b11011011 &
#458
b11011100 &
#460
b11011101 &
#462
b11011110 &
#464
b11011111 &
#466
b11100000 &
#468
b11100001 &
#470
b11100010 &
#472
b11100011 &
#474
b11100100 &
#476
b11100101 &
#478
b11100110 &
#480
b11100111 &
#482
b11101000 &
#484
b11101001 &
#486
b11101010 &
#488
b11101011 &
#490
b11101100 &
#492
b11101101 &
#494
b11101110 &
#496
b11101111 &
#498
b11110000 &
#500
b11110001 &
#502
b11110010 &
#504
b11110011 &
#506
b11110100 &
#508
b11110101 &
#510
b11110110 &
#512
b11110111 &
#514
b11111000 &
#516
b11111001 &
#518
b11111010 &
#520
b11111011 &
#522
b11111100 &
#524
b11111101 &
#526
b11111110 &
#528
b11111111 &
#530
b00000000 &
#532
b00000001 &
#534
b00000010 &
#536
b00000011 &
#538
b00000100 &
#540
b00000101 &
#542
b00000110 &
#544
b00000111 &
#546
b00001000 &
#548
0%
b00001001 &
#550
#552
#554
1%
#556
b00001010 &
#558
b00001011 &
#560
b00001100 &
#562
b00001101 &
#564
b00001110 &
#566
b00001111 &
#568
b00010000 &
#570
b00010001 &
#572
b00010010 &
#574
b00010011 &
#576
b00010100 &
#578
b00010101 &
#580
b00010110 &
#582
b00010111 &
#584
b00011000 &
#586
b00011001 &
#588
b00011010 &
#590
b00011011 &
#592
b00011100 &
#594
b00011101 &
#596
b00011110 &
#598
b00011111 &
